inte_form_validators/__init__.py
inte_form_validators/apps.py
inte_form_validators/models.py
inte_form_validators/form_validators/__init__.py
inte_form_validators/form_validators/crf_form_validator_mixin.py
inte_form_validators/form_validators/general_assessment_initial.py
inte_form_validators/form_validators/risk_factors.py
inte_form_validators/form_validators/subject_consent.py
inte_form_validators/form_validators/blood_results/__init__.py
inte_form_validators/form_validators/blood_results/blood_results_form_validator.py
inte_form_validators/form_validators/blood_results/blood_results_form_validator_mixin.py
inte_form_validators/tests/__init__.py
inte_form_validators/tests/test_form_validators.py
inte_form_validators/tests/test_general_assessment.py
inte_form_validators/tests/urls.py
inte_form_validators-0.1.3.dist-info/AUTHORS
inte_form_validators-0.1.3.dist-info/LICENSE
inte_form_validators-0.1.3.dist-info/METADATA
inte_form_validators-0.1.3.dist-info/WHEEL
inte_form_validators-0.1.3.dist-info/top_level.txt
inte_form_validators-0.1.3.dist-info/RECORD
