Metadata-Version: 2.1
Name: inte-form-validators
Version: 0.1.3
Summary: Form validators for inte/edc project
Home-page: https://github.com/inte-trial/inte-form-validators
Author: Erik van Widenfelt
Author-email: ew2789@gmail.com
License: GPL license, see LICENSE
Keywords: django inte
Platform: UNKNOWN
Classifier: Environment :: Web Environment
Classifier: Framework :: Django
Classifier: Intended Audience :: Developers
Classifier: Intended Audience :: Science/Research
Classifier: License :: OSI Approved :: GNU General Public License v3 (GPLv3)
Classifier: Operating System :: OS Independent
Classifier: Programming Language :: Python :: 3.7
Classifier: Topic :: Internet :: WWW/HTTP
Classifier: Topic :: Internet :: WWW/HTTP :: Dynamic Content
Requires-Python: >=3.7
Requires-Dist: pytz
Requires-Dist: edc-appointment
Requires-Dist: edc-constants
Requires-Dist: edc-form-validators
Requires-Dist: edc-lab
Requires-Dist: edc-reportable
Requires-Dist: inte-consent
Requires-Dist: inte-screening
